trainy/__init__.py
trainy/cli.py
trainy/constants.py
trainy/httpd.py
trainy/watcher.py
trainy-0.1.3.dist-info/METADATA
trainy-0.1.3.dist-info/WHEEL
trainy-0.1.3.dist-info/entry_points.txt
trainy-0.1.3.dist-info/top_level.txt
trainy-0.1.3.dist-info/RECORD
