Metadata-Version: 2.1
Name: trainy
Version: 0.1.3
Summary: Trainy: An observability tool for profiling PyTorch training on demand
Author: Trainy Team
License: Apache 2.0
Project-URL: Homepage, https://github.com/Trainy-ai/trainy
Classifier: Programming Language :: Python :: 3.7
Classifier: Programming Language :: Python :: 3.8
Classifier: Programming Language :: Python :: 3.9
Classifier: Programming Language :: Python :: 3.10
Classifier: License :: OSI Approved :: Apache Software License
Classifier: Operating System :: OS Independent
Classifier: Topic :: Software Development :: Libraries :: Python Modules
Classifier: Topic :: System :: Distributed Computing
Requires-Dist: wheel
Requires-Dist: ray[default] (==2.4.0)
Requires-Dist: torch (>=2.0.0)
Requires-Dist: gpustat (==1.0)
Requires-Dist: posthog
